MANIFEST.in
README.txt
setup.py
bookmarker/__init__.py
bookmarker/settings.py
bookmarker/templates/bookmarker/links.html
bookmarker/templatetags/__init__.py
bookmarker/templatetags/bookmarker_tags.py
django_bookmarker.egg-info/PKG-INFO
django_bookmarker.egg-info/SOURCES.txt
django_bookmarker.egg-info/dependency_links.txt
django_bookmarker.egg-info/top_level.txt