Metadata-Version: 1.0
Name: django-bookmarker
Version: 0.1.0
Summary: Social bookmark linsk
Home-page: http://bitbucket.org/lorien/django-bookmarker
Author: Grigoriy Petukhov
Author-email: lorien@lorien.name
License: BSD
Keywords: django application social bookmarks
Platform: UNKNOWN
Classifier: Development Status :: 4 - Beta
Classifier: Environment :: Web Environment
Classifier: Framework :: Django
Classifier: Intended Audience :: Developers
Classifier: License :: OSI Approved :: BSD License
Classifier: Operating System :: OS Independent
Classifier: Programming Language :: Python
Classifier: Topic :: Utilities
